giftwrap/__init__.py
giftwrap/misc_scripts.py
giftwrap/pipeline.py
giftwrap/py.typed
giftwrap/read_gf_h5.R
giftwrap/step1_count_gapfills.py
giftwrap/step2_correct_umis.py
giftwrap/step3_correct_gapfill.py
giftwrap/step4_collect_counts.py
giftwrap/step5_summarize_counts.py
giftwrap/utils.py
giftwrap/analysis/__init__.py
giftwrap/analysis/plots.py
giftwrap/analysis/preprocess.py
giftwrap/analysis/spatial.py
giftwrap/analysis/tools.py
giftwrap/resources/737K-fixed-rna-profiling.txt.gz
giftwrap/resources/737K-flex-v2.txt.gz
giftwrap/resources/README.md
giftwrap/resources/chemistry_defs.json
giftwrap/resources/flex-v2-384.txt
giftwrap/resources/visium-v1.txt
giftwrap/resources/visium-v1_coordinates.txt
giftwrap/resources/visium-v2.txt
giftwrap/resources/visium-v2_coordinates.txt
giftwrap/resources/visium-v3.txt
giftwrap/resources/visium-v3_coordinates.txt
giftwrap/resources/visium-v4.txt
giftwrap/resources/visium-v4_coordinates.txt
giftwrap/resources/visium-v5.txt
giftwrap/resources/visium-v5_coordinates.txt
giftwrap/resources/visium_hd_v1.slide
giftwrap_sc-0.3.0.dist-info/METADATA
giftwrap_sc-0.3.0.dist-info/WHEEL
giftwrap_sc-0.3.0.dist-info/entry_points.txt
giftwrap_sc-0.3.0.dist-info/licenses/LICENSE
giftwrap_sc-0.3.0.dist-info/RECORD
