Metadata-Version: 2.4
Name: giftwrap-sc
Version: 0.3.0
Summary: Tools to quantify GIFT-seq datasets.
Project-URL: Homepage, https://clareaulab.github.io/giftwrap
Project-URL: Documentation, https://clareaulab.github.io/giftwrap
Project-URL: Repository, https://github.com/lareauc/giftwrap
Project-URL: Issues, https://github.com/lareauc/giftwrap/issues
Author-email: "Austin A. Varela" <aav4003@med.cornell.edu>, "Caleb A. Lareau" <lareauc@mskcc.org>
License: MIT License
License-File: LICENSE
Keywords: GIFT-seq,gapfill
Classifier: Development Status :: 4 - Beta
Classifier: Intended Audience :: Science/Research
Classifier: License :: OSI Approved :: MIT License
Classifier: Programming Language :: Python :: 3
Classifier: Topic :: Scientific/Engineering :: Bio-Informatics
Requires-Python: >=3.11
Requires-Dist: anndata>=0.11
Requires-Dist: biopython>=1.85
Requires-Dist: h5py>=3.14
Requires-Dist: matplotlib>=3.10
Requires-Dist: numpy>=2.2.6
Requires-Dist: openpyxl>=3.1.5
Requires-Dist: pandas>=2.3.0
Requires-Dist: prefixtrie>=1.1.0
Requires-Dist: rich-argparse>=1.7.1
Requires-Dist: sankeyflow>=0.4.1
Requires-Dist: scipy>=1.15
Requires-Dist: tqdm>=4.66.5
Provides-Extra: all
Requires-Dist: adjusttext>=1.3.0; extra == 'all'
Requires-Dist: igraph>=0.10; extra == 'all'
Requires-Dist: numba>=0.61.0; extra == 'all'
Requires-Dist: protobuf>=5.28.0; extra == 'all'
Requires-Dist: rapidfuzz>=3.13; extra == 'all'
Requires-Dist: scanpy>=1.11; extra == 'all'
Requires-Dist: spatialdata-plot>=0.2.11; extra == 'all'
Requires-Dist: spatialdata>=0.5.0; extra == 'all'
Requires-Dist: squidpy>=1.6.5; extra == 'all'
Provides-Extra: analysis
Requires-Dist: adjusttext>=1.3.0; extra == 'analysis'
Requires-Dist: igraph>=0.10; extra == 'analysis'
Requires-Dist: leidenalg>=0.10.2; extra == 'analysis'
Requires-Dist: logomaker>=0.8.7; extra == 'analysis'
Requires-Dist: numba>=0.61.0; extra == 'analysis'
Requires-Dist: pyfamsa>=0.5.3.post1; extra == 'analysis'
Requires-Dist: rapidfuzz>=3.13; extra == 'analysis'
Requires-Dist: scanpy>=1.11; extra == 'analysis'
Provides-Extra: docs
Requires-Dist: griffe-inherited-docstrings>=1.1.1; extra == 'docs'
Requires-Dist: griffe-sphinx>=0.1.0; extra == 'docs'
Requires-Dist: markdown-exec[ansi]>=1.10.3; extra == 'docs'
Requires-Dist: mkdocs-api-autonav>=0.3.0; extra == 'docs'
Requires-Dist: mkdocs-autorefs>=1.4.2; extra == 'docs'
Requires-Dist: mkdocs-awesome-nav>=3.1.2; extra == 'docs'
Requires-Dist: mkdocs-awesome-pages-plugin>=2.10.1; extra == 'docs'
Requires-Dist: mkdocs-git-revision-date-localized-plugin>=1.4.7; extra == 'docs'
Requires-Dist: mkdocs-jupyter>=0.25.1; extra == 'docs'
Requires-Dist: mkdocs-material>=9.6.18; extra == 'docs'
Requires-Dist: mkdocs-open-in-new-tab>=1.0.8; extra == 'docs'
Requires-Dist: mkdocs-panzoom-plugin>=0.4.2; extra == 'docs'
Requires-Dist: mkdocstrings[python]>=0.29.1; extra == 'docs'
Requires-Dist: pymdown-extensions>=10.15; extra == 'docs'
Requires-Dist: termynal>=0.13.0; extra == 'docs'
Provides-Extra: spatial
Requires-Dist: protobuf>=5.28.0; extra == 'spatial'
Requires-Dist: spatialdata-plot>=0.2.11; extra == 'spatial'
Requires-Dist: spatialdata>=0.5.0; extra == 'spatial'
Requires-Dist: squidpy>=1.6.5; extra == 'spatial'
